jxl2txt/__init__.py
jxl2txt/jxl2txt.py
jxl2txt/tools/__init__.py
jxl2txt/tools/console.py
jxl2txt-0.1.0.dist-info/DESCRIPTION.rst
jxl2txt-0.1.0.dist-info/METADATA
jxl2txt-0.1.0.dist-info/RECORD
jxl2txt-0.1.0.dist-info/WHEEL
jxl2txt-0.1.0.dist-info/entry_points.txt
jxl2txt-0.1.0.dist-info/metadata.json
jxl2txt-0.1.0.dist-info/top_level.txt
