Metadata-Version: 2.0
Name: jxl2txt
Version: 0.1.0
Summary: Python library to convert Trimble JobXML files using XSLT
Home-page: http://github.com/mrahnis/jxl2txt
Author: Michael Rahnis
Author-email: michael.rahnis@fandm.edu
License: BSD
Keywords: survey,conversion
Platform: UNKNOWN
Classifier: Development Status :: 3 - Alpha
Classifier: License :: OSI Approved :: BSD License
Classifier: Programming Language :: Python
Classifier: Programming Language :: Python :: 2.7
Classifier: Programming Language :: Python :: 3
Classifier: Topic :: Scientific/Engineering :: GIS
Requires-Dist: click
Requires-Dist: lxml
